civic_geo_generator/__init__.py
civic_geo_generator/__main__.py
civic_geo_generator/_version.py
civic_geo_generator/index.py
civic_geo_generator/py.typed
civic_geo_generator/validate.py
civic_geo_generator/build/__init__.py
civic_geo_generator/build/config.py
civic_geo_generator/build/metadata.py
civic_geo_generator/build/pipeline.py
civic_geo_generator/cli/__init__.py
civic_geo_generator/cli/cli.py
civic_geo_generator/cli/run.py
civic_geo_generator/utils/__init__.py
civic_geo_generator/utils/context.py
civic_geo_generator/utils/layer_config.py
civic_geo_generator/utils/paths.py
civic_geo_generator/utils/validate_meta.py
civic_geo_generator-0.1.3.dist-info/licenses/LICENSE
civic_geo_generator-0.1.3.dist-info/METADATA
civic_geo_generator-0.1.3.dist-info/WHEEL
civic_geo_generator-0.1.3.dist-info/entry_points.txt
civic_geo_generator-0.1.3.dist-info/top_level.txt
civic_geo_generator-0.1.3.dist-info/RECORD
