Metadata-Version: 2.4
Name: civic-geo-generator
Version: 0.1.3
Summary: Build, validate, and index web-optimized GeoJSON precinct, school district, etc. files for state repos
Author-email: Civic Interconnect <info@civic-interconnect.org>
License-Expression: MIT
Project-URL: Documentation, https://civic-interconnect.github.io/civic-geo-generator/latest
Project-URL: Homepage, https://github.com/civic-interconnect/civic-geo-generator
Project-URL: Issues, https://github.com/civic-interconnect/civic-geo-generator/issues
Project-URL: Source, https://github.com/civic-interconnect/civic-geo-generator
Keywords: civic,elections,gis,geojson,boundaries,precincts,generator,publisher
Classifier: Development Status :: 4 - Beta
Classifier: Intended Audience :: Developers
Classifier: Intended Audience :: Science/Research
Classifier: Intended Audience :: Education
Classifier: Natural Language :: English
Classifier: Operating System :: OS Independent
Classifier: Programming Language :: Python :: 3
Classifier: Programming Language :: Python :: 3 :: Only
Classifier: Programming Language :: Python :: 3.12
Classifier: Programming Language :: Python :: 3.13
Classifier: Topic :: Scientific/Engineering :: GIS
Classifier: Topic :: Software Development :: Build Tools
Classifier: Typing :: Typed
Requires-Python: >=3.12
License-File: LICENSE
Requires-Dist: civic-lib-core
Requires-Dist: civic-lib-geo
Requires-Dist: geopandas
Requires-Dist: jsonschema[format]
Requires-Dist: PyYAML
Requires-Dist: typer
Provides-Extra: dev
Requires-Dist: pre-commit; extra == "dev"
Requires-Dist: pyright; extra == "dev"
Requires-Dist: pytest; extra == "dev"
Requires-Dist: pytest-cov; extra == "dev"
Requires-Dist: pytest-env; extra == "dev"
Requires-Dist: shapely; extra == "dev"
Requires-Dist: twine; extra == "dev"
Requires-Dist: validate-pyproject; extra == "dev"
Provides-Extra: docs
Requires-Dist: mike; extra == "docs"
Requires-Dist: mkdocs; extra == "docs"
Requires-Dist: mkdocs-gen-files; extra == "docs"
Requires-Dist: mkdocs-git-revision-date-localized-plugin; extra == "docs"
Requires-Dist: mkdocs-include-markdown-plugin; extra == "docs"
Requires-Dist: mkdocs-literate-nav; extra == "docs"
Requires-Dist: mkdocs-material; extra == "docs"
Requires-Dist: mkdocs-static-i18n; extra == "docs"
Requires-Dist: mkdocstrings[python]>=0.18; extra == "docs"
Requires-Dist: ruff; extra == "docs"
Dynamic: license-file
